acoustic_solo_dadagp-0.1.0.dist-info/licenses/LICENSE
asdadagp/__init__.py
asdadagp/_version.py
asdadagp/cli.py
asdadagp/const.py
asdadagp/decoder.py
asdadagp/encoder.py
asdadagp/processor.py
asdadagp/token_splitter.py
asdadagp/utils.py
asdadagp/examples/alphabet.txt
asdadagp/examples/ed_sheeran_photograph.gp5
asdadagp/examples/ed_sheeran_photograph.txt
asdadagp/examples/ed_sheeran_photograph_processed.txt
asdadagp/examples/ed_sheeran_supermarket_flowers.gp5
asdadagp/examples/ed_sheeran_supermarket_flowers.txt
asdadagp/examples/ed_sheeran_supermarket_flowers_merge_tracks.txt
asdadagp/examples/ed_sheeran_supermarket_flowers_processed.txt
asdadagp/examples/maroon5_payphone.gp5
asdadagp/examples/maroon5_payphone.txt
asdadagp/examples/maroon5_payphone_processed.txt
asdadagp/examples/merge_rest_test.txt
asdadagp/examples/merge_rest_test_processed.txt
asdadagp/examples/repeat_measure_test.txt
asdadagp/examples/repeat_measure_test_processed.txt
asdadagp/examples/test_measure_splitting.txt
acoustic_solo_dadagp-0.1.0.dist-info/METADATA
acoustic_solo_dadagp-0.1.0.dist-info/WHEEL
acoustic_solo_dadagp-0.1.0.dist-info/entry_points.txt
acoustic_solo_dadagp-0.1.0.dist-info/top_level.txt
acoustic_solo_dadagp-0.1.0.dist-info/RECORD
