Metadata-Version: 2.4
Name: acoustic-solo-dadaGP
Version: 0.1.0
Summary: Guitar tablature tokenization and processing toolkit.
Author-email: Austin Liu <austin_f_liu@brown.edu>, Claude Hu <zh4nh@virginia.edu>
License: MIT License
Project-URL: Homepage, https://github.com/austinliu05/acoustic-solo-dadaGP
Project-URL: Source, https://github.com/austinliu05/acoustic-solo-dadaGP
Keywords: music,guitar,tablature,tokenization,audio
Classifier: Development Status :: 4 - Beta
Classifier: Intended Audience :: Developers
Classifier: Intended Audience :: Science/Research
Classifier: License :: OSI Approved :: MIT License
Classifier: Programming Language :: Python :: 3 :: Only
Classifier: Programming Language :: Python :: 3.8
Classifier: Programming Language :: Python :: 3.9
Classifier: Programming Language :: Python :: 3.10
Classifier: Programming Language :: Python :: 3.11
Classifier: Programming Language :: Python :: 3.12
Classifier: Operating System :: OS Independent
Classifier: Topic :: Multimedia :: Sound/Audio
Classifier: Topic :: Software Development :: Libraries :: Python Modules
Classifier: Topic :: Text Processing
Requires-Python: >=3.8
License-File: LICENSE
Requires-Dist: PyGuitarPro>=0.9
Requires-Dist: pytest>=6.0.0
Provides-Extra: dev
Requires-Dist: pytest>=6.0.0; extra == "dev"
Requires-Dist: pytest-cov>=2.0.0; extra == "dev"
Dynamic: license-file
